generate_bes_from_template/MSI_to_BES.py
generate_bes_from_template/TEMPLATE_TASK.bes.mustache
generate_bes_from_template/__init__.py
generate_bes_from_template/action_createfile_from_file.py
generate_bes_from_template/action_prefetch_from_template.py
generate_bes_from_template/generate_bes_from_template.py
generate_bes_from_template-0.0.9.dist-info/METADATA
generate_bes_from_template-0.0.9.dist-info/WHEEL
generate_bes_from_template-0.0.9.dist-info/top_level.txt
generate_bes_from_template-0.0.9.dist-info/RECORD
