Metadata-Version: 2.1
Name: generate-bes-from-template
Version: 0.0.9
Summary: A python module for generating BigFix content
Home-page: https://github.com/jgstew/generate_bes_from_template
Author: JGStew
Author-email: noreply@jgstew.com
License: MIT
Project-URL: Bug Tracker, https://github.com/jgstew/generate_bes_from_template/issues
Project-URL: Source, https://github.com/jgstew/generate_bes_from_template/tree/master/src/generate_bes_from_template
Keywords: bigfix bes fixlet relevance xml
Classifier: Programming Language :: Python :: 3
Classifier: Programming Language :: Python :: 3.5
Classifier: License :: OSI Approved :: MIT License
Classifier: Operating System :: OS Independent
Classifier: Development Status :: 5 - Production/Stable
Classifier: Intended Audience :: Developers
Classifier: Topic :: Software Development :: Libraries :: Python Modules
Classifier: Topic :: System :: Systems Administration
Requires-Python: >=3.5
Requires-Dist: chevron
